README.md
setup.py
src/enigma_kostas/__init__.py
src/enigma_kostas/enigma_run.py
src/enigma_kostas/plugboard.py
src/enigma_kostas/rotors.py
src/uu_enigma_kostas.egg-info/PKG-INFO
src/uu_enigma_kostas.egg-info/SOURCES.txt
src/uu_enigma_kostas.egg-info/dependency_links.txt
src/uu_enigma_kostas.egg-info/top_level.txt